pipecat_tts_cache/__init__.py
pipecat_tts_cache/key_generator.py
pipecat_tts_cache/mixin.py
pipecat_tts_cache/models.py
pipecat_tts_cache/py.typed
pipecat_tts_cache/backends/__init__.py
pipecat_tts_cache/backends/base.py
pipecat_tts_cache/backends/memory.py
pipecat_tts_cache/backends/redis.py
pipecat_tts_cache-0.0.3.dist-info/licenses/LICENSE
pipecat_tts_cache-0.0.3.dist-info/METADATA
pipecat_tts_cache-0.0.3.dist-info/WHEEL
pipecat_tts_cache-0.0.3.dist-info/top_level.txt
pipecat_tts_cache-0.0.3.dist-info/RECORD
