Metadata-Version: 2.4
Name: pipecat-tts-cache
Version: 0.0.3
Summary: TTS caching integration for Pipecat to reduce API costs on repeated phrases
Author-email: Om Chauhan <omchauhan64408@gmail.com>
License-Expression: BSD-2-Clause
Project-URL: Homepage, https://github.com/omChauhanDev/pipecat-tts-cache
Project-URL: Documentation, https://github.com/omChauhanDev/pipecat-tts-cache#readme
Project-URL: Source, https://github.com/omChauhanDev/pipecat-tts-cache
Project-URL: Issues, https://github.com/omChauhanDev/pipecat-tts-cache/issues
Project-URL: Changelog, https://github.com/omChauhanDev/pipecat-tts-cache/blob/main/CHANGELOG.md
Keywords: pipecat,tts,cache,voice,ai,text-to-speech
Classifier: Development Status :: 4 - Beta
Classifier: Intended Audience :: Developers
Classifier: Topic :: Communications :: Conferencing
Classifier: Topic :: Multimedia :: Sound/Audio
Classifier: Topic :: Scientific/Engineering :: Artificial Intelligence
Requires-Python: >=3.10
License-File: LICENSE
Requires-Dist: pipecat-ai>=0.0.91
Requires-Dist: loguru~=0.7.3
Provides-Extra: redis
Requires-Dist: redis>=5.0.0; extra == "redis"
Provides-Extra: examples
Requires-Dist: pipecat-ai[cartesia,daily,deepgram,google,runner,silero,webrtc]>=0.0.98; extra == "examples"
Provides-Extra: all
Requires-Dist: pipecat-tts-cache[examples,redis]; extra == "all"
Dynamic: license-file
